mld/__init__.py
mld/config.py
mld/configurator.py
mld/main.py
mld/smiles_lookup.py
mld/util/__init__.py
mld/util/file_parser.py
scripts/__init__.py
scripts/cli.py
mld-0.0.2.dist-info/METADATA
mld-0.0.2.dist-info/WHEEL
mld-0.0.2.dist-info/entry_points.txt
mld-0.0.2.dist-info/top_level.txt
mld-0.0.2.dist-info/RECORD
