Metadata-Version: 2.1
Name: mld
Version: 0.0.2
Summary: Package to support MLD
Home-page: https://curematch.com
Author: romanjoffee
Author-email: rjugai@curematch.com
License: UNKNOWN
Platform: UNKNOWN
Classifier: Programming Language :: Python :: 3
Classifier: License :: OSI Approved :: Apache Software License
Classifier: Operating System :: OS Independent
Requires-Dist: psycopg2-binary (==2.8.3)
Requires-Dist: click (==7.0)
